metaccm/__init__.py
metaccm/diffStatistics.py
metaccm/metaccm.py
metaccm/metaccmpro.py
metaccm/weightCalculate.py
metaccm-1.0.1.dist-info/LICENSE
metaccm-1.0.1.dist-info/METADATA
metaccm-1.0.1.dist-info/WHEEL
metaccm-1.0.1.dist-info/top_level.txt
metaccm-1.0.1.dist-info/RECORD
